{
  "lang":"pt",
  "name":"pipeline",
  "version":"0.0.0",
  "spacy_version":">=3.4.1,<3.5.0",
  "description":"",
  "author":"",
  "email":"",
  "url":"",
  "license":"",
  "spacy_git_version":"5c2a00cef",
  "vectors":{
    "width":0,
    "vectors":0,
    "keys":0,
    "name":null,
    "mode":"default"
  },
  "labels":{
    "textcat":[
      "3_Ensino_Medio",
      "2_Ensino_Fundamental_II",
      "4_Ensino_Superior",
      "1_Ensino_Fundamental_I"
    ]
  },
  "pipeline":[
    "textcat"
  ],
  "components":[
    "textcat"
  ],
  "disabled":[

  ],
  "performance":{
    "cats_score":0.6562328156,
    "cats_score_desc":"macro F",
    "cats_micro_p":0.730964467,
    "cats_micro_r":0.6990291262,
    "cats_micro_f":0.7146401985,
    "cats_macro_p":0.749257188,
    "cats_macro_r":0.7015143192,
    "cats_macro_f":0.6562328156,
    "cats_macro_auc":0.7180231995,
    "cats_f_per_type":{
      "3_Ensino_Medio":{
        "p":0.9230769231,
        "r":0.2,
        "f":0.3287671233
      },
      "2_Ensino_Fundamental_II":{
        "p":0.5423728814,
        "r":0.8648648649,
        "f":0.6666666667
      },
      "4_Ensino_Superior":{
        "p":0.8315789474,
        "r":0.9634146341,
        "f":0.8926553672
      },
      "1_Ensino_Fundamental_I":{
        "p":0.7,
        "r":0.7777777778,
        "f":0.7368421053
      }
    },
    "cats_macro_auc_per_type":0.0,
    "textcat_loss":12.1233219752
  }
}